ALU.v
/*
 * v1.0 +
 * 增加了 and xor
 * 测试正确
*/
`include "SNAIL.h"

module ALU (
    input wire [7:0] A,
    input wire [7:0] B,
    input wire [3:0] op, // 功能码
    output wire [7:0] E,
    output wire [1:0] cc
);

    assign E = (op == `ADD)? A + B:
               (op == `SUB)? A - B:
               (op == `AND)? A & B:
               (op == `XOR)? A ^ B: 8'hxx;
    assign cc = {A == B, A > B}; // ==10, <00, >01

endmodule

ALU_TEST.v
`timescale 10ns/1ns

module ALU_TEST;
    wire [7:0] A, B;
    wire [3:0] op;
    wire [7:0] E;
    wire [1:0] cc;
    reg clk;
    reg [7:0] jcqa, jcqb;
    reg [3:0] jcqop;

// 实例化ALU
    ALU alu (
        .A(A), // .A代表模块端口, A代表实例
        .B(B),
        .op(op),
        .E(E),
        .cc(cc)
    );
    parameter CYCLE = 1.0;
    always #(CYCLE/2)clk <= ~clk;
    assign op = jcqop;
    assign A = jcqa;
    assign B = jcqb;

    initial begin
        clk = 1'b1;
        jcqa = 8'h03;
        jcqb = 8'h02;
        jcqop = 4'h0;
    #10
        $finish;
    end
    always @(posedge clk) begin
        $write("%3d ", A);
        $write("%3d ", B);
        $write("%3d ", op);
        $write("%3d \n", E);
        jcqb = jcqb + 1;
        jcqop = (jcqop + 1) % 4;
    end

    initial begin
        $dumpfile("ALU_TEST.vcd");
        $dumpvars(0, alu);
        $dumpvars(0, clk);
    end
    
endmodule

ALU_TEST.vcd
$date
	Wed Jun 09 15:33:04 2021
$end
$version
	Icarus Verilog
$end
$timescale
	1ns
$end
$scope module ALU_TEST $end
$scope module alu $end
$var wire 8 ! A [7:0] $end
$var wire 8 " B [7:0] $end
$var wire 8 # E [7:0] $end
$var wire 2 $ cc [1:0] $end
$var wire 4 % op [3:0] $end
$upscope $end
$upscope $end
$scope module ALU_TEST $end
$var reg 1 & clk $end
$upscope $end
$enddefinitions $end
#0
$dumpvars
1&
b0 %
b1 $
b101 #
b10 "
b11 !
$end
#5
0&
#10
b0 #
b1 %
b10 $
b11 "
1&
#15
0&
#20
b0 #
b10 %
b0 $
b100 "
1&
#25
0&
#30
b110 #
b11 %
b101 "
1&
#35
0&
#40
b1001 #
b0 %
b110 "
1&
#45
0&
#50
b100 #
b1 %
b111 "
1&
#55
0&
#60
b0 #
b10 %
b1000 "
1&
#65
0&
#70
b1010 #
b11 %
b1001 "
1&
#75
0&
#80
b1101 #
b0 %
b1010 "
1&
#85
0&
#90
b1000 #
b1 %
b1011 "
1&
