ALU.v
/*
 * v1.0 +
 * 增加了 and xor
 * 测试正确
*/
`include "SNAIL.h"

module ALU (
    input wire [7:0] A,
    input wire [7:0] B,
    input wire [3:0] op, // 功能码
    output wire [7:0] E,
    output wire [1:0] cc
);

    assign E = (op == `ADD)? A + B:
               (op == `SUB)? A - B:
               (op == `AND)? A & B:
               (op == `XOR)? A ^ B: 8'hxx;
    assign cc = {A == B, A > B}; // ==10, <00, >01

endmodule

REGFILE.v
module REGFILE (
    input wire [2:0] srcA, // 指定A的源寄存器
    input wire [2:0] srcB, // 指定B的源寄存器
    output wire [7:0] A,
    output wire [7:0] B,
    input wire [2:0] dstM, // 指定M的目标寄存器
    input wire [2:0] dstE, // 指定E的目标寄存器
    input wire [7:0] M,
    input wire [7:0] E,
    input wire clk
);

    reg [7:0] rf [0:7];

    assign A = (srcA == 3'o0)? 8'h00: rf[srcA];
    assign B = (srcB == 3'o0)? 8'h00: rf[srcB];

    always @(posedge clk) begin
        if (dstM != 3'o0)
            rf[dstM] <= M;
        if (dstE != 3'o0 && dstE != dstM)
            rf[dstE] <= E;
    end
    
endmodule

PC.v
module PC (
    input wire [7:0] new_PC,
    output reg [7:0] PC,
    input wire clk,
    input wire rst_
);

    always @(posedge clk, negedge rst_) begin
        if (rst_ == 1'b0)
            PC <= 0;
        else
            PC <= new_PC;
    end
    
endmodule

SNAIL.v
/*
 * v1.0 + ing
 * 
 *
 */
`include "SNAIL.h"

// [ins fun][ra rb][rc]
`define ins rom_data[23:20]
`define fun rom_data[19:16]
// `define rA rom_data[14:12]
// `define rB rom_data[10:8]
// `define rC rom_data[6:4]

module SNAIL (
    output wire [7:0] ram_addr,
    output wire [7:0] ram_wdat,
    input wire [7:0] ram_rdat,
    output wire ram_rd_, ram_wr_,

    output wire [7:0] rom_addr,
    input wire [23:0] rom_data,

    input wire clk, rst_
);

    wire [7:0] valA, aluA, valB, aluB, valC, valE, valM, valP;
    wire [1:0] cc;
    wire [2:0] rA, rB, rC, dstM, dstE;
    wire [7:0] new_PC;

    PC pc(
        .new_PC(new_PC),
        .PC(rom_addr),
        .clk(clk),
        .rst_(rst_)
    );

    REGFILE regfile(
        .srcA(rA),
        .srcB(rB),
        .A(valA),
        .B(valB),
        .dstM(dstM),
        .dstE(dstE),
        .M(valM),
        .E(valE),
        .clk(clk)
    ); // r7为堆栈指针寄存器

    ALU alu(
        .A(aluA),
        .B(aluB),
        .op(`fun), // 功能码
        .E(valE),
        .cc(cc)
    );

    assign rA = (`ins == `RET)? `r7: rom_data[14:12];
    assign rB = (`ins == `RET || `ins == `CALL ||
        `ins == `PUSH || `ins == `POP)? `r7: rom_data[10:8];
    assign rC = rom_data[6:4];
    assign valC = (
        `ins == `JXX && `fun == `JMP || `ins == `CALL)? rom_data[15:8]: rom_data[7:0];
    assign valP = rom_addr + (
        (`ins == `HLT)? 0: // 不再向下读指令
        (`ins == `NOP || `ins == `RET)? 1: // NOP、RET占1B
        // 其他指令加3B
        (`ins == `JXX && `fun == `JMP ||
        `ins == `PUSH || `ins == `POP || `ins == `CALL)? 2:3);
    assign aluA = (`ins == `CALL || `ins == `PUSH)? -1:
        (`ins == `RET || `ins == `POP)?1: valA;
    assign aluB = (
        (`ins == `LD) ||
        (`ins == `ST) ||
        (`ins == `OPI))? valC: valB;
    
    // 访存
    assign ram_addr = (`ins == `RET)? valA:
        (`ins == `POP)? valB: valE;
    assign ram_wdat = (`ins == `PUSH)? valA:
        (`ins == `CALL)? valP: valB;
    assign ram_rd_ = (`ins == `LD || `ins == `RET || `ins == `POP)? 1'b0: 1'b1;
    assign ram_wr_ = (`ins == `ST || `ins == `PUSH || `ins == `CALL)? 1'b0: 1'b1;
    // 写回
    assign valM = ram_rdat;
    assign dstM = (`ins == `POP)? rA:
        (`ins == `LD)? rB: 3'o0; // 3'0: r0寄存器
    assign dstE = 
        (`ins == `CALL || `ins == `RET || `ins == `PUSH || `ins == `POP)? `r7:
        (`ins == `OPR)? rC:
        (`ins == `OPI)? rB: 3'o0;

    assign new_PC = 
    (( // 跳转指令
        `ins == `JXX && (
        `fun == `JMP ||
        `fun == `BEQ && cc[1:1] ||
        `fun == `BNE && ~cc[1:1] ||
        `fun == `BLT && ~cc[1:1] && ~cc[0:0] ||
        `fun == `BGT && cc[0:0])
    ) || `ins == `CALL)? valC:
    (`ins == `RET)? valM: valP;
endmodule

ROM.v
// 组合逻辑电路, 只读指令, 不写入
module ROM (
    input wire [7:0] addr, // 输入 地址
    output wire [23:0] out // 输出 读出的指令, 指令最长占 3B
);

    reg [7:0] mem[0:255];
    
    assign out = {mem[addr], mem[addr+1], mem[addr+2]}; // 读连续的 3B

    // initial begin
    //     $readmemh("ROM.txt", mem, 0, 255); // 从文件中读入提前写好的程序
    // end

endmodule

RAM.v
module RAM (
    input wire [7:0] addr, // 输入 地址
    input wire [7:0] in,  // 输入 数据
    output wire [7:0] out, // 输出 数据
    input wire rd_, // 读使能
    input wire wr_, // 写使能
    input wire clk // 时钟
);

    reg [7:0] mem[0:255]; // 数组, 256个8位单元

// 连续赋值, 读电路是逻辑组合电路
    assign out = (rd_ == 1'b0)? mem[addr]: 8'hxx;

// mem 是寄存器变量, 只能在 always 中赋值
    always @(posedge clk) begin
        if (wr_ == 1'b0) begin
            mem[addr] <= in;
        end
    end
    
endmodule

SNAIL_TEST.v
`timescale 10ns/1ns
`include "SNAIL.h"
`define ins rom_out[23:20]

module SNAIL_TEST;
    wire [7:0] ram_addr, ram_in, ram_out, rom_addr;
    wire [23:0] rom_out;
    wire rd_, wr_;
    reg clk, rst_;

    parameter CYCLE = 1.0;

    RAM ram(
        .addr(ram_addr),
        .in(ram_in),
        .out(ram_out),
        .rd_(rd_),
        .wr_(wr_),
        .clk(clk)
    );

    ROM rom(
        .addr(rom_addr),
        .out(rom_out)
    );

    SNAIL cpu(
        .ram_addr(ram_addr),
        .ram_wdat(ram_in),
        .ram_rdat(ram_out),
        .ram_rd_(rd_),
        .ram_wr_(wr_),
        .rom_addr(rom_addr),
        .rom_data(rom_out),
        .clk(clk),
        .rst_(rst_)
    );

    always #(CYCLE/2) clk <= ~clk;

    integer i;

    always @(negedge clk) begin
        if (rst_ && (`ins == `HLT)) #(CYCLE + 0.1) $finish;
        $write("%3d: ", $stime);
        // $write("d- %h %h %h\n", rom_out[24:16], rom_out[15:8], rom_out[7:0]);
        for (i = 0; i < 1; i = i + 1) begin
            if (ram.mem[i] !== 8'hxx)
                $write(" %c ", ram.mem[i]);
                // $write(" %d ", ram.mem[i]);
            else
                $write(" . ");
        end
        $write("\n");
    end

    initial begin
        $dumpfile("SNAIL_TEST.vcd");  // 指定波形文件
        $dumpvars;  // 默认所有变量
        $readmemh("RAM.txt", ram.mem, 0, 255);  // 读十六进制文件到变量
        $readmemh("ROM.txt", rom.mem, 0, 255);
        clk = 1'b1;
        rst_ = 1'b0;
        #(CYCLE + CYCLE / 2) rst_ = ~rst_;
    end

endmodule

SNAIL_TEST.vcd
$date
	Tue Jun 15 18:18:59 2021
$end
$version
	Icarus Verilog
$end
$timescale
	1ns
$end
$scope module SNAIL_TEST $end
$var wire 8 ! ram_addr [7:0] $end
$var wire 8 " ram_in [7:0] $end
$var wire 8 # ram_out [7:0] $end
$var wire 1 $ rd_ $end
$var wire 8 % rom_addr [7:0] $end
$var wire 24 & rom_out [23:0] $end
$var wire 1 ' wr_ $end
$var reg 1 ( clk $end
$var integer 32 ) i [31:0] $end
$var reg 1 * rst_ $end
$scope module ram $end
$var wire 8 + addr [7:0] $end
$var wire 1 , clk $end
$var wire 8 - in [7:0] $end
$var wire 8 . out [7:0] $end
$var wire 1 $ rd_ $end
$var wire 1 ' wr_ $end
$upscope $end
$scope module rom $end
$var wire 8 / addr [7:0] $end
$var wire 24 0 out [23:0] $end
$upscope $end
$scope module cpu $end
$var wire 8 1 aluA [7:0] $end
$var wire 8 2 aluB [7:0] $end
$var wire 2 3 cc [1:0] $end
$var wire 1 , clk $end
$var wire 3 4 dstE [2:0] $end
$var wire 3 5 dstM [2:0] $end
$var wire 8 6 new_PC [7:0] $end
$var wire 3 7 rA [2:0] $end
$var wire 3 8 rB [2:0] $end
$var wire 3 9 rC [2:0] $end
$var wire 8 : ram_addr [7:0] $end
$var wire 1 $ ram_rd_ $end
$var wire 8 ; ram_rdat [7:0] $end
$var wire 8 < ram_wdat [7:0] $end
$var wire 1 ' ram_wr_ $end
$var wire 8 = rom_addr [7:0] $end
$var wire 24 > rom_data [23:0] $end
$var wire 1 ? rst_ $end
$var wire 8 @ valA [7:0] $end
$var wire 8 A valB [7:0] $end
$var wire 8 B valC [7:0] $end
$var wire 8 C valE [7:0] $end
$var wire 8 D valM [7:0] $end
$var wire 8 E valP [7:0] $end
$scope module pc $end
$var wire 1 , clk $end
$var wire 8 F new_PC [7:0] $end
$var wire 1 ? rst_ $end
$var reg 8 G PC [7:0] $end
$upscope $end
$scope module regfile $end
$var wire 8 H A [7:0] $end
$var wire 8 I B [7:0] $end
$var wire 8 J E [7:0] $end
$var wire 8 K M [7:0] $end
$var wire 1 , clk $end
$var wire 3 L dstE [2:0] $end
$var wire 3 M dstM [2:0] $end
$var wire 3 N srcA [2:0] $end
$var wire 3 O srcB [2:0] $end
$upscope $end
$scope module alu $end
$var wire 8 P A [7:0] $end
$var wire 8 Q B [7:0] $end
$var wire 8 R E [7:0] $end
$var wire 2 S cc [1:0] $end
$var wire 4 T op [3:0] $end
$upscope $end
$upscope $end
$upscope $end
$enddefinitions $end
#0
$dumpvars
b0 T
b0 S
b110000 R
b110000 Q
b0 P
b111 O
b0 N
b0 M
b111 L
bx K
b110000 J
bx I
b0 H
b0 G
b11 F
b11 E
bx D
b110000 C
b110000 B
bx A
b0 @
0?
b10000000000011100110000 >
b0 =
bx <
bx ;
b110000 :
b11 9
b111 8
b0 7
b11 6
b0 5
b111 4
b0 3
b110000 2
b0 1
b10000000000011100110000 0
b0 /
bx .
bx -
1,
b110000 +
0*
bx )
1(
1'
b10000000000011100110000 &
b0 %
1$
bx #
bx "
b110000 !
$end
#5
b1 )
0(
0,
#10
b110000 "
b110000 -
b110000 <
b110000 A
b110000 I
1(
1,
#15
b1 )
0(
0,
1*
1?
#20
b1 !
b1 +
b1 :
b1 4
b1 L
bx "
bx -
bx <
b1 C
b1 J
b1 R
b110 6
b110 F
b1 2
b1 Q
bx A
bx I
b1 B
b1 8
b1 O
b110 E
b0 9
b11 G
b10000000000000100000001 &
b10000000000000100000001 0
b10000000000000100000001 >
b11 %
b11 /
b11 =
1(
1,
#25
b1 )
0(
0,
#30
b101111 !
b101111 +
b101111 :
b110000 2
b110000 Q
b101111 C
b101111 J
b101111 R
0'
b111 4
b111 L
b1000 6
b1000 F
b1 @
b1 H
b1 3
b1 S
b11111111 1
b11111111 P
b1110000 B
b1 7
b1 N
b111 8
b111 O
b1 "
b1 -
b1 <
b110000 A
b110000 I
b1000 E
b111 9
b110 G
b11000000001000001110000 &
b11000000001000001110000 0
b11000000001000001110000 >
b110 %
b110 /
b110 =
1(
1,
#35
b1 )
0(
0,
#40
b1 D
b1 K
b1 #
b1 .
b1 ;
1'
b110000 C
b110000 J
b110000 R
b1010 6
b1010 F
bx @
bx H
b0 3
b0 S
b1 1
b1 P
0$
b101111 2
b101111 Q
b100000 B
b10 7
b10 N
b101111 "
b101111 -
b101111 <
b10 5
b10 M
b101111 A
b101111 I
b1010 E
b10 9
b1000 G
b11100000010000000100000 &
b11100000010000000100000 0
b11100000010000000100000 >
b1000 %
b1000 /
b1000 =
1(
1,
#45
b1 )
0(
0,
#50
b0 1
b0 P
b10 3
b10 S
bx D
bx K
bx #
bx .
bx ;
0'
b1 "
b1 -
b1 <
b0 C
b0 J
b0 R
b1101 6
b1101 F
b1 8
b1 O
b0 !
b0 +
b0 :
1$
b0 4
b0 L
b0 2
b0 Q
b0 B
b0 7
b0 N
b0 5
b0 M
b1 A
b1 I
b0 @
b0 H
b1101 E
b0 9
b1010 G
b1000000000000100000000 &
b1000000000000100000000 0
b1000000000000100000000 >
b1010 %
b1010 /
b1010 =
1(
1,
#55
b1 )
0(
0,
#60
b110000 !
b110000 +
b110000 :
b110000 C
b110000 J
b110000 R
b1 3
b1 S
b110000 1
b110000 P
b0 "
b0 -
b0 <
1'
b1110 6
b1110 F
b110000 @
b110000 H
b0 A
b0 I
bx B
b111 7
b111 N
b0 8
b0 O
b1110 E
bx 9
b1101 G
b11110000xxxxxxxx &
b11110000xxxxxxxx 0
b11110000xxxxxxxx >
b1101 %
b1101 /
b1101 =
1(
1,
#65
b1 )
0(
0,
#70
bx !
bx +
bx :
bx 1
bx P
bx "
bx -
bx <
bx C
bx J
bx R
bx 3
bx S
bx 2
bx Q
b1110 6
b1110 F
bx @
bx H
bx A
bx I
bx 7
bx N
bx 8
bx O
b1110 E
b1110 G
b11110000xxxxxxxxxxxxxxxx &
b11110000xxxxxxxxxxxxxxxx 0
b11110000xxxxxxxxxxxxxxxx >
b1110 %
b1110 /
b1110 =
1(
1,
