ALU.v
module ALU (
    input wire [7:0] A,
    input wire [7:0] B,
    input wire [3:0] op, // 功能码
    output wire [7:0] E,
    output wire [1:0] cc
);

    assign E = (op == 4'h0)? A + B:
               (op == 4'h1)? A - B: 8'hxx;
    assign cc = {A == B, A > B}; // ==10, <00, >01

endmodule

REGFILE.v
module REGFILE (
    input wire [2:0] srcA, // 指定A的源寄存器
    input wire [2:0] srcB, // 指定B的源寄存器
    output wire [7:0] A,
    output wire [7:0] B,
    input wire [2:0] dstM, // 指定M的目标寄存器
    input wire [2:0] dstE, // 指定E的目标寄存器
    input wire [7:0] M,
    input wire [7:0] E,
    input wire clk
);

    reg [7:0] rf [0:7];

    assign A = (srcA == 3'b000)? 8'h00: rf[srcA];
    assign B = (srcB == 3'b000)? 8'h00: rf[srcB];

    always @(posedge clk) begin
        if (dstM != 3'o0)
            rf[dstM] <= M;
        if (dstE != 3'o0 && dstE != dstM)
            rf[dstE] <= E;
        
    end
    
endmodule

PC.v
module PC (
    input wire [7:0] new_PC,
    output reg [7:0] PC,
    input wire clk,
    input wire rst_
);

    always @(posedge clk, negedge rst_) begin
        if (rst_ == 1'b0)
            PC <= 0;
        else
            PC <= new_PC;
    end
    
endmodule

SNAIL.v
`include "SNAIL.h"

// [ins fun][ra rb][rc]
`define ins rom_data[23:20]
`define fun rom_data[19:16]
`define rA rom_data[14:12]
`define rB rom_data[10:8]
`define rC rom_data[6:4]

module SNAIL (
    output wire [7:0] ram_addr,
    output wire [7:0] ram_wdat,
    input wire [7:0] ram_rdat,
    output wire ram_rd_, ram_wr_,

    output wire [7:0] rom_addr,
    input wire [23:0] rom_data,

    input wire clk, rst_
);

    wire [7:0] valA, valB, aluB, valC, valE, valM, valP;
    wire [1:0] cc;
    wire [2:0] dstM, dstE;
    wire [7:0] new_PC;

    PC pc(
        .new_PC(new_PC),
        .PC(rom_addr),
        .clk(clk),
        .rst_(rst_)
    );

    REGFILE regfile(
        .srcA(`rA),
        .srcB(`rB),
        .A(valA),
        .B(valB),
        .dstM(dstM),
        .dstE(dstE),
        .M(valM),
        .E(valE),
        .clk(clk)
    );

    ALU alu(
        .A(valA),
        .B(aluB),
        .op(`fun), // 功能码
        .E(valE),
        .cc(cc)
    );

    assign valC = (`ins == `JXX && `fun == `JMP)? rom_data[15:8]: rom_data[7:0];
    assign valP = rom_addr + (
        (`ins == `HLT)? 0: // 不再向下读指令
        (`ins == `NOP)? 1: // NOP指令占1B
        (`ins == `JXX && `fun == `JMP)? 2:3); // JMP指令跳到操作数处, 其他指令加3B
    assign aluB = (
        (`ins == `LD) ||
        (`ins == `ST) ||
        (`ins == `OPI))? valC: valB;
    
    // 访存
    assign ram_addr = valE;
    assign ram_wdat = valB;
    assign ram_rd_ = (`ins == `LD)? 1'b0: 1'b1;
    assign ram_wr_ = (`ins == `ST)? 1'b0: 1'b1;

    assign valM = ram_rdat;
    assign dstM = (`ins == `LD)? `rB: 3'o0; // 3'0: r0寄存器
    assign dstE = (`ins == `OPR)? `rC:
        (`ins == `OPI)? `rB: 3'o0;

    assign new_PC = (`ins == `JXX && (
        `fun == `JMP ||
        `fun == `BEQ && cc[1:1] ||
        `fun == `BNE && ~cc[1:1] ||
        `fun == `BLT && ~cc[1:1] && ~cc[0:0] ||
        `fun == `BGT && cc[0:0]))? valC: valP;
endmodule

ROM.v
// 组合逻辑电路, 只读指令, 不写入
module ROM (
    input wire [7:0] addr, // 输入 地址
    output wire [23:0] out // 输出 读出的指令, 指令最长占 3B
);

    reg [7:0] mem[0:255];
    
    assign out = {mem[addr], mem[addr+1], mem[addr+2]}; // 读连续的 3B

    // initial begin
    //     $readmemh("ROM.txt", mem, 0, 255); // 从文件中读入提前写好的程序
    // end

endmodule

RAM.v
module RAM (
    input wire [7:0] addr, // 输入 地址
    input wire [7:0] in,  // 输入 数据
    output wire [7:0] out, // 输出 数据
    input wire rd_, // 读使能
    input wire wr_, // 写使能
    input wire clk // 时钟
);

    reg [7:0] mem[0:255]; // 数组, 256个8位单元

// 连续赋值, 读电路是逻辑组合电路
    assign out = (rd_ == 1'b0)? mem[addr]: 8'hxx;

// mem 是寄存器变量, 只能在 always 中赋值
    always @(posedge clk) begin
        if (wr_ == 1'b0) begin
            mem[addr] <= in;
        end
    end
    
endmodule

SNAIL_TEST.v
`timescale 10ns/1ns
`include "SNAIL.h"
`define ins rom_out[23:20]
`define fun rom_out[19:16]
`define rA rom_out[14:12]
`define rB rom_out[10:8]
`define rC rom_out[6:0]

module SNAIL_TEST;
    wire [7:0] ram_addr, ram_in, ram_out, rom_addr;
    wire [23:0] rom_out;
    wire rd_, wr_;
    reg clk, rst_;

    parameter CYCLE = 1.0;

    RAM ram(
        .addr(ram_addr),
        .in(ram_in),
        .out(ram_out),
        .rd_(rd_),
        .wr_(wr_),
        .clk(clk)
    );

    ROM rom(
        .addr(rom_addr),
        .out(rom_out)
    );

    SNAIL cpu(
        .ram_addr(ram_addr),
        .ram_wdat(ram_in),
        .ram_rdat(ram_out),
        .ram_rd_(rd_),
        .ram_wr_(wr_),
        .rom_addr(rom_addr),
        .rom_data(rom_out),
        .clk(clk),
        .rst_(rst_)
    );

    always #(CYCLE/2) clk <= ~clk;

    integer i;

    always @(negedge clk) begin
        if (rst_ && (`ins == `HLT)) #(CYCLE + 0.1) $finish;
        // $write("d- %h%h %h%h %h\n", `ins, `fun, `rA, `rB, `rC);
        $write("%3d: ", $stime);
        for (i = 0; i < 32; i = i + 1) begin
            if (ram.mem[i] !== 8'hxx)
                $write(" %c ", ram.mem[i]);
            else
                $write(" . ");
        end
        $write("\n");
    end

    // always @(posedge clk) begin
    //     $write("u- %h%h %h%h %h\n", `ins, `fun, `rA, `rB, `rC);
    // end

    initial begin
        $dumpfile("SNAIL_TEST.vcd");  // 指定波形文件
        $dumpvars;  // 默认所有变量
        $readmemh("RAM.txt", ram.mem, 0, 255);  // 读十六进制文件到变量
        $readmemh("ROM.txt", rom.mem, 0, 255);
        clk = 1'b1;
        rst_ = 1'b0;
        #(CYCLE + CYCLE / 2) rst_ = ~rst_;
    end

endmodule

SNAIL_TEST.vcd
$date
	Tue Jun 08 14:10:39 2021
$end
$version
	Icarus Verilog
$end
$timescale
	1ns
$end
$scope module SNAIL_TEST $end
$var wire 8 ! ram_addr [7:0] $end
$var wire 8 " ram_in [7:0] $end
$var wire 8 # ram_out [7:0] $end
$var wire 1 $ rd_ $end
$var wire 8 % rom_addr [7:0] $end
$var wire 24 & rom_out [23:0] $end
$var wire 1 ' wr_ $end
$var reg 1 ( clk $end
$var integer 32 ) i [31:0] $end
$var reg 1 * rst_ $end
$scope module ram $end
$var wire 8 + addr [7:0] $end
$var wire 1 , clk $end
$var wire 8 - in [7:0] $end
$var wire 8 . out [7:0] $end
$var wire 1 $ rd_ $end
$var wire 1 ' wr_ $end
$upscope $end
$scope module rom $end
$var wire 8 / addr [7:0] $end
$var wire 24 0 out [23:0] $end
$upscope $end
$scope module cpu $end
$var wire 8 1 aluB [7:0] $end
$var wire 2 2 cc [1:0] $end
$var wire 1 , clk $end
$var wire 3 3 dstE [2:0] $end
$var wire 3 4 dstM [2:0] $end
$var wire 8 5 new_PC [7:0] $end
$var wire 8 6 ram_addr [7:0] $end
$var wire 1 $ ram_rd_ $end
$var wire 8 7 ram_rdat [7:0] $end
$var wire 8 8 ram_wdat [7:0] $end
$var wire 1 ' ram_wr_ $end
$var wire 8 9 rom_addr [7:0] $end
$var wire 24 : rom_data [23:0] $end
$var wire 1 ; rst_ $end
$var wire 8 < valA [7:0] $end
$var wire 8 = valB [7:0] $end
$var wire 8 > valC [7:0] $end
$var wire 8 ? valE [7:0] $end
$var wire 8 @ valM [7:0] $end
$var wire 8 A valP [7:0] $end
$scope module pc $end
$var wire 1 , clk $end
$var wire 8 B new_PC [7:0] $end
$var wire 1 ; rst_ $end
$var reg 8 C PC [7:0] $end
$upscope $end
$scope module regfile $end
$var wire 8 D A [7:0] $end
$var wire 8 E B [7:0] $end
$var wire 8 F E [7:0] $end
$var wire 8 G M [7:0] $end
$var wire 1 , clk $end
$var wire 3 H dstE [2:0] $end
$var wire 3 I dstM [2:0] $end
$var wire 3 J srcA [2:0] $end
$var wire 3 K srcB [2:0] $end
$upscope $end
$scope module alu $end
$var wire 8 L A [7:0] $end
$var wire 8 M B [7:0] $end
$var wire 8 N E [7:0] $end
$var wire 2 O cc [1:0] $end
$var wire 4 P op [3:0] $end
$upscope $end
$upscope $end
$upscope $end
$enddefinitions $end
#0
$dumpvars
b0 P
b10 O
b0 N
b0 M
b0 L
b1 K
b0 J
b0 I
b1 H
bx G
b0 F
bx E
b0 D
b0 C
b11 B
b11 A
bx @
b0 ?
b0 >
bx =
b0 <
0;
b10000000000000100000000 :
b0 9
bx 8
bx 7
b0 6
b11 5
b0 4
b1 3
b10 2
b0 1
b10000000000000100000000 0
b0 /
bx .
bx -
1,
b0 +
0*
bx )
1(
1'
b10000000000000100000000 &
b0 %
1$
bx #
bx "
b0 !
$end
#5
b100000 )
0(
0,
#10
b0 =
b0 E
b0 "
b0 -
b0 8
1(
1,
#15
b100000 )
0(
0,
1*
1;
#20
b0 ?
b0 F
b0 N
b0 !
b0 +
b0 6
b1000001 @
b1000001 G
b1000001 #
b1000001 .
b1000001 7
b10 2
b10 O
b0 1
b0 M
b0 3
b0 H
b110 5
b110 B
bx =
bx E
bx "
bx -
bx 8
0$
b10 4
b10 I
b110 A
b1 J
b10 K
b11 C
b100000001001000000000 &
b100000001001000000000 0
b100000001001000000000 :
b11 %
b11 /
b11 9
1(
1,
#25
b100000 )
0(
0,
#30
bx @
bx G
bx #
bx .
bx 7
b1010 5
b1010 B
b1010 >
b1 2
b1 O
b1000001 <
b1000001 D
b1000001 L
bx ?
bx F
bx N
bx !
bx +
bx 6
1$
b0 4
b0 I
b0 =
b0 E
b0 "
b0 -
b0 8
b1001 A
b10 J
b0 K
b10 P
b110 C
b10100100010000000001010 &
b10100100010000000001010 0
b10100100010000000001010 :
b110 %
b110 /
b110 9
1(
1,
#35
b100000 )
0(
0,
#40
b1000001 1
b1000001 M
b11 3
b11 H
b1101 5
b1101 B
b1000001 >
b0 2
b0 O
b0 <
b0 D
b0 L
bx =
bx E
bx "
bx -
bx 8
b1000001 ?
b1000001 F
b1000001 N
b1000001 !
b1000001 +
b1000001 6
b1101 A
b0 J
b11 K
b0 P
b1010 C
b10000000000001101000001 &
b10000000000001101000001 0
b10000000000001101000001 :
b1010 %
b1010 /
b1010 9
1(
1,
#45
b100000 )
0(
0,
#50
b0 3
b0 H
b10000 5
b10000 B
b110000 >
b10 2
b10 O
b1000001 <
b1000001 D
b1000001 L
bx ?
bx F
bx N
bx !
bx +
bx 6
b1000001 =
b1000001 E
b1000001 "
b1000001 -
b1000001 8
b10000 A
b10 J
b11 P
b1101 C
b10100110010001100110000 &
b10100110010001100110000 0
b10100110010001100110000 :
b1101 %
b1101 /
b1101 9
1(
1,
#55
b100000 )
0(
0,
#60
b1111010 1
b1111010 M
b11 3
b11 H
b10011 5
b10011 B
b1111010 >
b0 2
b0 O
b0 <
b0 D
b0 L
b1111010 ?
b1111010 F
b1111010 N
b1111010 !
b1111010 +
b1111010 6
b10011 A
b0 J
b0 P
b10000 C
b10000000000001101111010 &
b10000000000001101111010 0
b10000000000001101111010 :
b10000 %
b10000 /
b10000 9
1(
1,
#65
b100000 )
0(
0,
#70
b0 3
b0 H
b10110 5
b10110 B
b110000 >
b1000001 <
b1000001 D
b1000001 L
bx ?
bx F
bx N
bx !
bx +
bx 6
b1111010 =
b1111010 E
b1111010 "
b1111010 -
b1111010 8
b10110 A
b10 J
b100 P
b10011 C
b10101000010001100110000 &
b10101000010001100110000 0
b10101000010001100110000 :
b10011 %
b10011 /
b10011 9
1(
1,
#75
b100000 )
0(
0,
#80
b1011010 1
b1011010 M
b11 3
b11 H
b11001 5
b11001 B
b1011010 >
b0 <
b0 D
b0 L
b1011010 ?
b1011010 F
b1011010 N
b1011010 !
b1011010 +
b1011010 6
b11001 A
b0 J
b0 P
b10110 C
b10000000000001101011010 &
b10000000000001101011010 0
b10000000000001101011010 :
b10110 %
b10110 /
b10110 9
1(
1,
#85
b100000 )
0(
0,
#90
b0 3
b0 H
b11100 5
b11100 B
b100100 >
b1000001 <
b1000001 D
b1000001 L
bx ?
bx F
bx N
bx !
bx +
bx 6
b1011010 =
b1011010 E
b1011010 "
b1011010 -
b1011010 8
b11100 A
b10 J
b100 P
b11001 C
b10101000010001100100100 &
b10101000010001100100100 0
b10101000010001100100100 :
b11001 %
b11001 /
b11001 9
1(
1,
#95
b100000 )
0(
0,
#100
b1 2
b1 O
b100000 1
b100000 M
b10 3
b10 H
b11111 5
b11111 B
b100000 >
b1000001 =
b1000001 E
b1000001 "
b1000001 -
b1000001 8
b1100001 ?
b1100001 F
b1100001 N
b1100001 !
b1100001 +
b1100001 6
b11111 A
b10 K
b0 P
b11100 C
b10000000010001000100000 &
b10000000010001000100000 0
b10000000010001000100000 :
b11100 %
b11100 /
b11100 9
1(
1,
#105
b100000 )
0(
0,
#110
b0 1
b0 M
b0 3
b0 H
b0 ?
b0 F
b0 N
b0 !
b0 +
b0 6
b100010 5
b100010 B
b0 >
0'
b10 2
b10 O
b0 <
b0 D
b0 L
b1100001 =
b1100001 E
b1100001 "
b1100001 -
b1100001 8
b100010 A
b1 J
b11111 C
b1000000001001000000000 &
b1000000001001000000000 0
b1000000001001000000000 :
b11111 %
b11111 /
b11111 9
1(
1,
#115
b100000 )
0(
0,
#120
b1011010 ?
b1011010 F
b1011010 N
b1011010 !
b1011010 +
b1011010 6
b110000 5
b110000 B
b110000 >
b1 2
b1 O
b1011010 <
b1011010 D
b1011010 L
b0 =
b0 E
b0 "
b0 -
b0 8
1'
b100100 A
b11 J
b0 K
b100010 C
b10100000011000001000000 &
b10100000011000001000000 0
b10100000011000001000000 :
b100010 %
b100010 /
b100010 9
1(
1,
#125
b100000 )
0(
0,
#130
b1 ?
b1 F
b1 N
b1 !
b1 +
b1 6
b1 1
b1 M
b1 3
b1 H
b110011 5
b110011 B
b0 2
b0 O
b0 <
b0 D
b0 L
b1 >
b110011 A
b1 J
b1 K
b110000 C
b10000000001000100000001 &
b10000000001000100000001 0
b10000000001000100000001 :
b110000 %
b110000 /
b110000 9
1(
1,
#135
b100000 )
0(
0,
#140
b1011010 ?
b1011010 F
b1011010 N
b1011010 !
b1011010 +
b1011010 6
b1011010 1
b1011010 M
b0 3
b0 H
b11 5
b11 B
b11 >
b1011010 =
b1011010 E
b1011010 "
b1011010 -
b1011010 8
b110101 A
b0 J
b11 K
b110011 C
b101000000000011xxxxxxxx &
b101000000000011xxxxxxxx 0
b101000000000011xxxxxxxx :
b110011 %
b110011 /
b110011 9
1(
1,
#145
b100000 )
0(
0,
#150
b110000 @
b110000 G
b110000 #
b110000 .
b110000 7
b1 ?
b1 F
b1 N
b1 !
b1 +
b1 6
b1 2
b1 O
b0 1
b0 M
b110 5
b110 B
b1 <
b1 D
b1 L
b1100001 =
b1100001 E
b1100001 "
b1100001 -
b1100001 8
b0 >
0$
b10 4
b10 I
b110 A
b1 J
b10 K
b11 C
b100000001001000000000 &
b100000001001000000000 0
b100000001001000000000 :
b11 %
b11 /
b11 9
1(
1,
#155
b100000 )
0(
0,
#160
bx @
bx G
bx #
bx .
bx 7
b1010 5
b1010 B
b1010 >
b110000 <
b110000 D
b110000 L
bx ?
bx F
bx N
bx !
bx +
bx 6
1$
b0 4
b0 I
b0 =
b0 E
b0 "
b0 -
b0 8
b1001 A
b10 J
b0 K
b10 P
b110 C
b10100100010000000001010 &
b10100100010000000001010 0
b10100100010000000001010 :
b110 %
b110 /
b110 9
1(
1,
#165
b100000 )
0(
0,
#170
b1000001 1
b1000001 M
b11 3
b11 H
b1101 5
b1101 B
b1000001 >
b0 2
b0 O
b0 <
b0 D
b0 L
b1011010 =
b1011010 E
b1011010 "
b1011010 -
b1011010 8
b1000001 ?
b1000001 F
b1000001 N
b1000001 !
b1000001 +
b1000001 6
b1101 A
b0 J
b11 K
b0 P
b1010 C
b10000000000001101000001 &
b10000000000001101000001 0
b10000000000001101000001 :
b1010 %
b1010 /
b1010 9
1(
1,
#175
b100000 )
0(
0,
#180
b0 3
b0 H
b110000 5
b110000 B
b110000 >
b110000 <
b110000 D
b110000 L
bx ?
bx F
bx N
bx !
bx +
bx 6
b1000001 =
b1000001 E
b1000001 "
b1000001 -
b1000001 8
b10000 A
b10 J
b11 P
b1101 C
b10100110010001100110000 &
b10100110010001100110000 0
b10100110010001100110000 :
b1101 %
b1101 /
b1101 9
1(
1,
#185
b100000 )
0(
0,
#190
b10 2
b10 O
b1 1
b1 M
b1 3
b1 H
b110011 5
b110011 B
b1 >
b1 <
b1 D
b1 L
b1 =
b1 E
b1 "
b1 -
b1 8
b10 ?
b10 F
b10 N
b10 !
b10 +
b10 6
b110011 A
b1 J
b1 K
b0 P
b110000 C
b10000000001000100000001 &
b10000000001000100000001 0
b10000000001000100000001 :
b110000 %
b110000 /
b110000 9
1(
1,
#195
b100000 )
0(
0,
#200
b1000001 1
b1000001 M
b0 3
b0 H
b1000001 ?
b1000001 F
b1000001 N
b1000001 !
b1000001 +
b1000001 6
b11 5
b11 B
b11 >
b0 2
b0 O
b0 <
b0 D
b0 L
b1000001 =
b1000001 E
b1000001 "
b1000001 -
b1000001 8
b110101 A
b0 J
b11 K
b110011 C
b101000000000011xxxxxxxx &
b101000000000011xxxxxxxx 0
b101000000000011xxxxxxxx :
b110011 %
b110011 /
b110011 9
1(
1,
#205
b100000 )
0(
0,
#210
b1100001 @
b1100001 G
b1100001 #
b1100001 .
b1100001 7
b10 ?
b10 F
b10 N
b10 !
b10 +
b10 6
b1 2
b1 O
b0 1
b0 M
b110 5
b110 B
b10 <
b10 D
b10 L
b110000 =
b110000 E
b110000 "
b110000 -
b110000 8
b0 >
0$
b10 4
b10 I
b110 A
b1 J
b10 K
b11 C
b100000001001000000000 &
b100000001001000000000 0
b100000001001000000000 :
b11 %
b11 /
b11 9
1(
1,
#215
b100000 )
0(
0,
#220
bx @
bx G
bx #
bx .
bx 7
b1010 5
b1010 B
b1010 >
b1100001 <
b1100001 D
b1100001 L
bx ?
bx F
bx N
bx !
bx +
bx 6
1$
b0 4
b0 I
b0 =
b0 E
b0 "
b0 -
b0 8
b1001 A
b10 J
b0 K
b10 P
b110 C
b10100100010000000001010 &
b10100100010000000001010 0
b10100100010000000001010 :
b110 %
b110 /
b110 9
1(
1,
#225
b100000 )
0(
0,
#230
b1000001 1
b1000001 M
b11 3
b11 H
b1101 5
b1101 B
b1000001 >
b0 2
b0 O
b0 <
b0 D
b0 L
b1000001 =
b1000001 E
b1000001 "
b1000001 -
b1000001 8
b1000001 ?
b1000001 F
b1000001 N
b1000001 !
b1000001 +
b1000001 6
b1101 A
b0 J
b11 K
b0 P
b1010 C
b10000000000001101000001 &
b10000000000001101000001 0
b10000000000001101000001 :
b1010 %
b1010 /
b1010 9
1(
1,
#235
b100000 )
0(
0,
#240
b0 3
b0 H
b10000 5
b10000 B
b110000 >
b1 2
b1 O
b1100001 <
b1100001 D
b1100001 L
bx ?
bx F
bx N
bx !
bx +
bx 6
b10000 A
b10 J
b11 P
b1101 C
b10100110010001100110000 &
b10100110010001100110000 0
b10100110010001100110000 :
b1101 %
b1101 /
b1101 9
1(
1,
#245
b100000 )
0(
0,
#250
b1111010 1
b1111010 M
b11 3
b11 H
b10011 5
b10011 B
b1111010 >
b0 2
b0 O
b0 <
b0 D
b0 L
b1111010 ?
b1111010 F
b1111010 N
b1111010 !
b1111010 +
b1111010 6
b10011 A
b0 J
b0 P
b10000 C
b10000000000001101111010 &
b10000000000001101111010 0
b10000000000001101111010 :
b10000 %
b10000 /
b10000 9
1(
1,
#255
b100000 )
0(
0,
#260
b0 3
b0 H
b10110 5
b10110 B
b110000 >
b1100001 <
b1100001 D
b1100001 L
bx ?
bx F
bx N
bx !
bx +
bx 6
b1111010 =
b1111010 E
b1111010 "
b1111010 -
b1111010 8
b10110 A
b10 J
b100 P
b10011 C
b10101000010001100110000 &
b10101000010001100110000 0
b10101000010001100110000 :
b10011 %
b10011 /
b10011 9
1(
1,
#265
b100000 )
0(
0,
#270
b1011010 1
b1011010 M
b11 3
b11 H
b11001 5
b11001 B
b1011010 >
b0 <
b0 D
b0 L
b1011010 ?
b1011010 F
b1011010 N
b1011010 !
b1011010 +
b1011010 6
b11001 A
b0 J
b0 P
b10110 C
b10000000000001101011010 &
b10000000000001101011010 0
b10000000000001101011010 :
b10110 %
b10110 /
b10110 9
1(
1,
#275
b100000 )
0(
0,
#280
b0 3
b0 H
b100100 5
b100100 B
b100100 >
b1 2
b1 O
b1100001 <
b1100001 D
b1100001 L
bx ?
bx F
bx N
bx !
bx +
bx 6
b1011010 =
b1011010 E
b1011010 "
b1011010 -
b1011010 8
b11100 A
b10 J
b100 P
b11001 C
b10101000010001100100100 &
b10101000010001100100100 0
b10101000010001100100100 :
b11001 %
b11001 /
b11001 9
1(
1,
#285
b100000 )
0(
0,
#290
b1100001 1
b1100001 M
b11 3
b11 H
b100111 5
b100111 B
b1100001 >
b0 2
b0 O
b0 <
b0 D
b0 L
b1100001 ?
b1100001 F
b1100001 N
b1100001 !
b1100001 +
b1100001 6
b100111 A
b0 J
b0 P
b100100 C
b10000000000001101100001 &
b10000000000001101100001 0
b10000000000001101100001 :
b100100 %
b100100 /
b100100 9
1(
1,
#295
b100000 )
0(
0,
#300
b0 3
b0 H
b101010 5
b101010 B
b110000 >
b10 2
b10 O
b1100001 <
b1100001 D
b1100001 L
bx ?
bx F
bx N
bx !
bx +
bx 6
b1100001 =
b1100001 E
b1100001 "
b1100001 -
b1100001 8
b101010 A
b10 J
b11 P
b100111 C
b10100110010001100110000 &
b10100110010001100110000 0
b10100110010001100110000 :
b100111 %
b100111 /
b100111 9
1(
1,
#305
b100000 )
0(
0,
#310
b1000001 ?
b1000001 F
b1000001 N
b1000001 !
b1000001 +
b1000001 6
b1 2
b1 O
b100000 1
b100000 M
b10 3
b10 H
b101101 5
b101101 B
b100000 >
b101101 A
b10 K
b1 P
b101010 C
b10000010010001000100000 &
b10000010010001000100000 0
b10000010010001000100000 :
b101010 %
b101010 /
b101010 9
1(
1,
#315
b100000 )
0(
0,
#320
b0 1
b0 M
b0 3
b0 H
b110000 5
b110000 B
b0 >
b10 ?
b10 F
b10 N
b10 !
b10 +
b10 6
0'
b1 2
b1 O
b10 <
b10 D
b10 L
b1000001 =
b1000001 E
b1000001 "
b1000001 -
b1000001 8
b110000 A
b1 J
b0 P
b101101 C
b1000000001001000000000 &
b1000000001001000000000 0
b1000000001001000000000 :
b101101 %
b101101 /
b101101 9
1(
1,
#325
b100000 )
0(
0,
#330
b11 ?
b11 F
b11 N
b11 !
b11 +
b11 6
b1 1
b1 M
b1 3
b1 H
b110011 5
b110011 B
b1 >
b10 =
b10 E
b10 "
b10 -
b10 8
1'
b110011 A
b1 K
b110000 C
b10000000001000100000001 &
b10000000001000100000001 0
b10000000001000100000001 :
b110000 %
b110000 /
b110000 9
1(
1,
#335
b100000 )
0(
0,
#340
b1100001 1
b1100001 M
b0 3
b0 H
b1100001 ?
b1100001 F
b1100001 N
b1100001 !
b1100001 +
b1100001 6
b11 5
b11 B
b11 >
b0 2
b0 O
b0 <
b0 D
b0 L
b1100001 =
b1100001 E
b1100001 "
b1100001 -
b1100001 8
b110101 A
b0 J
b11 K
b110011 C
b101000000000011xxxxxxxx &
b101000000000011xxxxxxxx 0
b101000000000011xxxxxxxx :
b110011 %
b110011 /
b110011 9
1(
1,
#345
b100000 )
0(
0,
#350
b110001 @
b110001 G
b110001 #
b110001 .
b110001 7
b11 ?
b11 F
b11 N
b11 !
b11 +
b11 6
b1 2
b1 O
b0 1
b0 M
b110 5
b110 B
b11 <
b11 D
b11 L
b1000001 =
b1000001 E
b1000001 "
b1000001 -
b1000001 8
b0 >
0$
b10 4
b10 I
b110 A
b1 J
b10 K
b11 C
b100000001001000000000 &
b100000001001000000000 0
b100000001001000000000 :
b11 %
b11 /
b11 9
1(
1,
#355
b100000 )
0(
0,
#360
bx @
bx G
bx #
bx .
bx 7
b1010 5
b1010 B
b1010 >
b110001 <
b110001 D
b110001 L
bx ?
bx F
bx N
bx !
bx +
bx 6
1$
b0 4
b0 I
b0 =
b0 E
b0 "
b0 -
b0 8
b1001 A
b10 J
b0 K
b10 P
b110 C
b10100100010000000001010 &
b10100100010000000001010 0
b10100100010000000001010 :
b110 %
b110 /
b110 9
1(
1,
#365
b100000 )
0(
0,
#370
b1000001 1
b1000001 M
b11 3
b11 H
b1101 5
b1101 B
b1000001 >
b0 2
b0 O
b0 <
b0 D
b0 L
b1100001 =
b1100001 E
b1100001 "
b1100001 -
b1100001 8
b1000001 ?
b1000001 F
b1000001 N
b1000001 !
b1000001 +
b1000001 6
b1101 A
b0 J
b11 K
b0 P
b1010 C
b10000000000001101000001 &
b10000000000001101000001 0
b10000000000001101000001 :
b1010 %
b1010 /
b1010 9
1(
1,
#375
b100000 )
0(
0,
#380
b0 3
b0 H
b110000 5
b110000 B
b110000 >
b110001 <
b110001 D
b110001 L
bx ?
bx F
bx N
bx !
bx +
bx 6
b1000001 =
b1000001 E
b1000001 "
b1000001 -
b1000001 8
b10000 A
b10 J
b11 P
b1101 C
b10100110010001100110000 &
b10100110010001100110000 0
b10100110010001100110000 :
b1101 %
b1101 /
b1101 9
1(
1,
#385
b100000 )
0(
0,
#390
b1 2
b1 O
b1 1
b1 M
b1 3
b1 H
b110011 5
b110011 B
b1 >
b11 <
b11 D
b11 L
b11 =
b11 E
b11 "
b11 -
b11 8
b100 ?
b100 F
b100 N
b100 !
b100 +
b100 6
b110011 A
b1 J
b1 K
b0 P
b110000 C
b10000000001000100000001 &
b10000000001000100000001 0
b10000000001000100000001 :
b110000 %
b110000 /
b110000 9
1(
1,
#395
b100000 )
0(
0,
#400
b1000001 1
b1000001 M
b0 3
b0 H
b1000001 ?
b1000001 F
b1000001 N
b1000001 !
b1000001 +
b1000001 6
b11 5
b11 B
b11 >
b0 2
b0 O
b0 <
b0 D
b0 L
b1000001 =
b1000001 E
b1000001 "
b1000001 -
b1000001 8
b110101 A
b0 J
b11 K
b110011 C
b101000000000011xxxxxxxx &
b101000000000011xxxxxxxx 0
b101000000000011xxxxxxxx :
b110011 %
b110011 /
b110011 9
1(
1,
#405
b100000 )
0(
0,
#410
b1000010 @
b1000010 G
b1000010 #
b1000010 .
b1000010 7
b100 ?
b100 F
b100 N
b100 !
b100 +
b100 6
b1 2
b1 O
b0 1
b0 M
b110 5
b110 B
b100 <
b100 D
b100 L
b110001 =
b110001 E
b110001 "
b110001 -
b110001 8
b0 >
0$
b10 4
b10 I
b110 A
b1 J
b10 K
b11 C
b100000001001000000000 &
b100000001001000000000 0
b100000001001000000000 :
b11 %
b11 /
b11 9
1(
1,
#415
b100000 )
0(
0,
#420
bx @
bx G
bx #
bx .
bx 7
b1010 5
b1010 B
b1010 >
b1000010 <
b1000010 D
b1000010 L
bx ?
bx F
bx N
bx !
bx +
bx 6
1$
b0 4
b0 I
b0 =
b0 E
b0 "
b0 -
b0 8
b1001 A
b10 J
b0 K
b10 P
b110 C
b10100100010000000001010 &
b10100100010000000001010 0
b10100100010000000001010 :
b110 %
b110 /
b110 9
1(
1,
#425
b100000 )
0(
0,
#430
b1000001 1
b1000001 M
b11 3
b11 H
b1101 5
b1101 B
b1000001 >
b0 2
b0 O
b0 <
b0 D
b0 L
b1000001 =
b1000001 E
b1000001 "
b1000001 -
b1000001 8
b1000001 ?
b1000001 F
b1000001 N
b1000001 !
b1000001 +
b1000001 6
b1101 A
b0 J
b11 K
b0 P
b1010 C
b10000000000001101000001 &
b10000000000001101000001 0
b10000000000001101000001 :
b1010 %
b1010 /
b1010 9
1(
1,
#435
b100000 )
0(
0,
#440
b0 3
b0 H
b10000 5
b10000 B
b110000 >
b1 2
b1 O
b1000010 <
b1000010 D
b1000010 L
bx ?
bx F
bx N
bx !
bx +
bx 6
b10000 A
b10 J
b11 P
b1101 C
b10100110010001100110000 &
b10100110010001100110000 0
b10100110010001100110000 :
b1101 %
b1101 /
b1101 9
1(
1,
#445
b100000 )
0(
0,
#450
b1111010 1
b1111010 M
b11 3
b11 H
b10011 5
b10011 B
b1111010 >
b0 2
b0 O
b0 <
b0 D
b0 L
b1111010 ?
b1111010 F
b1111010 N
b1111010 !
b1111010 +
b1111010 6
b10011 A
b0 J
b0 P
b10000 C
b10000000000001101111010 &
b10000000000001101111010 0
b10000000000001101111010 :
b10000 %
b10000 /
b10000 9
1(
1,
#455
b100000 )
0(
0,
#460
b0 3
b0 H
b10110 5
b10110 B
b110000 >
b1000010 <
b1000010 D
b1000010 L
bx ?
bx F
bx N
bx !
bx +
bx 6
b1111010 =
b1111010 E
b1111010 "
b1111010 -
b1111010 8
b10110 A
b10 J
b100 P
b10011 C
b10101000010001100110000 &
b10101000010001100110000 0
b10101000010001100110000 :
b10011 %
b10011 /
b10011 9
1(
1,
#465
b100000 )
0(
0,
#470
b1011010 1
b1011010 M
b11 3
b11 H
b11001 5
b11001 B
b1011010 >
b0 <
b0 D
b0 L
b1011010 ?
b1011010 F
b1011010 N
b1011010 !
b1011010 +
b1011010 6
b11001 A
b0 J
b0 P
b10110 C
b10000000000001101011010 &
b10000000000001101011010 0
b10000000000001101011010 :
b10110 %
b10110 /
b10110 9
1(
1,
#475
b100000 )
0(
0,
